README.rst
_description.org
lh-agpl3-LICENSE.txt
pyproject.toml
setup.py
bin/csRo-manage.cs
bin/exmpl-plantedCsu.cs
bin/plantedHelloWorld.cs
bin/seededCmnds.cs
bisos/__init__.py
bisos.b.egg-info/PKG-INFO
bisos.b.egg-info/SOURCES.txt
bisos.b.egg-info/dependency_links.txt
bisos.b.egg-info/not-zip-safe
bisos.b.egg-info/requires.txt
bisos.b.egg-info/top_level.txt
bisos/b/__init__.py
bisos/b/ast.py
bisos/b/clsMethod_csu.py
bisos/b/cmndsSeed.py
bisos/b/comment.py
bisos/b/dir.py
bisos/b/exception.py
bisos/b/fp.py
bisos/b/fpCls.py
bisos/b/fp_csu.py
bisos/b/fpath.py
bisos/b/fto.py
bisos/b/fv.py
bisos/b/importFile.py
bisos/b/niche.py
bisos/b/op.py
bisos/b/pyRunAs-obsoleted.py
bisos/b/pyRunAs.py
bisos/b/seededCmnds_seed.py
bisos/b/subProc.py
bisos/b/types.py
bisos/b/utils.py
bisos/b/b_io/__init__.py
bisos/b/b_io/ann.py
bisos/b/b_io/eh.py
bisos/b/b_io/io.py
bisos/b/b_io/log.py
bisos/b/b_io/out.py
bisos/b/b_io/stderr.py
bisos/b/b_io/stdin.py
bisos/b/b_io/stdout.py
bisos/b/b_io/tm.py
bisos/b/cs/__init__.py
bisos/b/cs/arg.py
bisos/b/cs/cs.py
bisos/b/cs/examples.py
bisos/b/cs/globalContext.py
bisos/b/cs/inCmnd.py
bisos/b/cs/main.py
bisos/b/cs/param.py
bisos/b/cs/ro.py
bisos/b/cs/rpyc.py
bisos/b/cs/rtInvoker.py
bisos/b/cs/runArgs.py
bisos/b/cs/track.py